MANIFEST.in
README.txt
setup.py
docs/HISTORY.txt
docs/INSTALL.txt
docs/LICENSE.GPL
docs/LICENSE.txt
rer/__init__.py
rer.portlet.er_navigation.egg-info/PKG-INFO
rer.portlet.er_navigation.egg-info/SOURCES.txt
rer.portlet.er_navigation.egg-info/dependency_links.txt
rer.portlet.er_navigation.egg-info/entry_points.txt
rer.portlet.er_navigation.egg-info/namespace_packages.txt
rer.portlet.er_navigation.egg-info/not-zip-safe
rer.portlet.er_navigation.egg-info/requires.txt
rer.portlet.er_navigation.egg-info/top_level.txt
rer/portlet/__init__.py
rer/portlet/er_navigation/__init__.py
rer/portlet/er_navigation/configure.zcml
rer/portlet/er_navigation/er_navigation_recurse.pt
rer/portlet/er_navigation/erportletnavigation.pt
rer/portlet/er_navigation/erportletnavigation.py
rer/portlet/er_navigation/i18n.sh
rer/portlet/er_navigation/i18n/plone-it.po
rer/portlet/er_navigation/locales/rer.portlet.er_navigation.pot
rer/portlet/er_navigation/locales/it/LC_MESSAGES/rer.portlet.er_navigation.mo
rer/portlet/er_navigation/locales/it/LC_MESSAGES/rer.portlet.er_navigation.po
rer/portlet/er_navigation/profiles/default/metadata.xml
rer/portlet/er_navigation/profiles/default/portlets.xml
rer/portlet/er_navigation/tests/__init__.py
rer/portlet/er_navigation/tests/base.py
rer/portlet/er_navigation/tests/test_portlet.py