Metadata-Version: 1.1
Name: rer.portlet.er-navigation
Version: 1.0.7
Summary: A custom navigation portlet for ER portal
Home-page: http://svn.plone.org/svn/collective/
Author: RedTurtle Technology
Author-email: sviluppoplone@redturtle.net
License: GPL
Keywords: portlet navigation
Platform: UNKNOWN
Classifier: Framework :: Plone
Classifier: Programming Language :: Python
